neat_panda/__init__.py
neat_panda/_caretaker.py
neat_panda/_clipboard_wsl.py
neat_panda/_helpers.py
neat_panda/_set_operations.py
neat_panda/_tidy.py
neat_panda-0.9.8.1.dist-info/LICENSE
neat_panda-0.9.8.1.dist-info/WHEEL
neat_panda-0.9.8.1.dist-info/METADATA
neat_panda-0.9.8.1.dist-info/RECORD
