Metadata-Version: 2.1
Name: neat-panda
Version: 0.9.8.1
Summary: 
Home-page: https://github.com/htp84/neat_panda
Author: Henric Sundberg,
Author-email: henric.sundberg@gmail.com
Requires-Python: >=3.7,<4.0
Classifier: Development Status :: 4 - Beta
Classifier: Intended Audience :: Developers
Classifier: License :: OSI Approved :: MIT License
Classifier: Natural Language :: English
Classifier: Programming Language :: Python :: 3
Classifier: Programming Language :: Python :: 3.7
Classifier: Programming Language :: Python :: 3.8
Classifier: Programming Language :: Python :: 3.9
Classifier: Topic :: Software Development :: Libraries :: Python Modules
Provides-Extra: pyperclip
Requires-Dist: pandas (>=1.0.3)
Requires-Dist: pandas_flavor (>=0.1.2)
Requires-Dist: pyperclip (>=1.8.2,<2.0.0); extra == "pyperclip"
Requires-Dist: toml (>=0.10.0)
